README.md
setup.py
bin/oxtimelines
oxtimelines/__init__.py
oxtimelines/ffmpeg.py
oxtimelines/timeline.py
oxtimelines.egg-info/PKG-INFO
oxtimelines.egg-info/SOURCES.txt
oxtimelines.egg-info/dependency_links.txt
oxtimelines.egg-info/top_level.txt