Metadata-Version: 2.1
Name: oxtimelines
Version: 0.50
Summary: extract timelines from videos
Home-page: https://wiki.0x2620.org/wiki/oxtimelines
Download-URL: http://code.0x2620.org/oxtimelines/download
Author: 0x2620
Author-email: 0x2620@0x2620.org
License: GPLv3
Classifier: Development Status :: 5 - Production/Stable
Classifier: Operating System :: OS Independent
Classifier: Programming Language :: Python
Classifier: Topic :: Software Development :: Libraries :: Python Modules
Classifier: Topic :: Utilities
